pyautoev/SSHTunnel.py
pyautoev/__init__.py
pyautoev/datetime_utils.py
pyautoev/generate.py
pyautoev/measure.py
pyautoev/mongop.py
pyautoev/mysqlp.py
pyautoev/mysqlpd.py
pyautoev/redisp.py
pyautoev/sqlitep.py
pyautoev/unittest_util.py
pyautoev-0.1.3.dist-info/METADATA
pyautoev-0.1.3.dist-info/WHEEL
pyautoev-0.1.3.dist-info/top_level.txt
pyautoev-0.1.3.dist-info/RECORD
