Metadata-Version: 2.1
Name: pyautoev
Version: 0.1.3
Summary: club is public library
Home-page: 
Author: Isee
Author-email: 
Requires-Dist: sshtunnel==0.4.0
Requires-Dist: PyMySQL==1.1.1
Requires-Dist: SQLAlchemy==2.0.32
Requires-Dist: redis==5.2.0
Requires-Dist: pymongo==4.13.0
Requires-Dist: PyYAML==6.0.2
Requires-Dist: pytz==2024.2; python_version < "3.10"
Requires-Dist: pandas==2.1.2; python_version < "3.10"
Requires-Dist: pandas==2.2.3; python_version >= "3.10"
